pyscales.py
pyscales-1.0.2.dist-info/DESCRIPTION.rst
pyscales-1.0.2.dist-info/METADATA
pyscales-1.0.2.dist-info/RECORD
pyscales-1.0.2.dist-info/WHEEL
pyscales-1.0.2.dist-info/metadata.json
pyscales-1.0.2.dist-info/top_level.txt
