Metadata-Version: 2.0
Name: pyscales
Version: 1.0.2
Summary: Simple arithmetic on musical notes
Home-page: https://bitbucket.org/talljosh/pyscales
Author: J. D. Bartlett
Author-email: josh@bartletts.id.au
License: MIT
Keywords: music scales notes midi
Platform: UNKNOWN
Classifier: Development Status :: 5 - Production/Stable
Classifier: Intended Audience :: Developers
Classifier: License :: OSI Approved :: MIT License
Classifier: Programming Language :: Python :: 2
Classifier: Programming Language :: Python :: 2.7
Classifier: Programming Language :: Python :: 3
Classifier: Programming Language :: Python :: 3.5
